dask_searchcv/__init__.py
dask_searchcv/_compat.py
dask_searchcv/_normalize.py
dask_searchcv/_version.py
dask_searchcv/methods.py
dask_searchcv/model_selection.py
dask_searchcv/utils.py
dask_searchcv/utils_test.py
dask_searchcv/tests/__init__.py
dask_searchcv/tests/test_model_selection.py
dask_searchcv/tests/test_model_selection_sklearn.py
dask_searchcv-0.2.0.dist-info/DESCRIPTION.rst
dask_searchcv-0.2.0.dist-info/METADATA
dask_searchcv-0.2.0.dist-info/RECORD
dask_searchcv-0.2.0.dist-info/WHEEL
dask_searchcv-0.2.0.dist-info/metadata.json
dask_searchcv-0.2.0.dist-info/top_level.txt
