Metadata-Version: 1.0
Name: dask-searchcv
Version: 0.2.0
Summary: Tools for doing hyperparameter search with Scikit-Learn and Dask
Home-page: http://github.com/dask/dask-searchcv
Author: Jim Crist
Author-email: jcrist@continuum.io
License: BSD
Platform: UNKNOWN
